{
  "2026-06": {
    "OP": 11,
    "RPP": 33,
    "MCL": 35,
    "CJ": 29,
    "CLC": 58,
    "MCJ": 35,
    "RC": 17,
    "LA": 15,
    "RM": 28,
    "LCM": 21,
    "TLS": 31,
    "CL": 28,
    "LS": 18,
    "LJC": 9,
    "PC": 13,
    "MMR": 12,
    "TS": 22,
    "ÑJ": 20,
    "TSA": 21,
    "RB": 43,
    "CF": 16,
    "RS": 26,
    "FCT": 9,
    "PCM": 9,
    "ÑP": 14,
    "TF": 8,
    "MCC": 15,
    "CAMA": 38,
    "TPP": 10,
    "RA": 13,
    "AS": 12,
    "PAC": 23,
    "EM": 17,
    "ÑC": 19,
    "EJ": 15,
    "BAP": 10,
    "MIGNON": 16,
    "PV": 16,
    "TA": 17,
    "MMRM": 14,
    "LR": 6,
    "CP": 15,
    "LSA": 9,
    "RJ": 10,
    "CM": 17,
    "TCM": 11,
    "PCP": 54,
    "EC": 11,
    "CC": 9,
    "SSA": 9,
    "BAR": 4,
    "LM": 4,
    "CAC": 6,
    "TPU": 8,
    "SA": 27,
    "CAMAC": 0
  }
}